code_team/__init__.py
code_team/__main__.py
code_team/py.typed
code_team/agents/__init__.py
code_team/agents/base.py
code_team/agents/coder.py
code_team/agents/committer.py
code_team/agents/plan_verifier.py
code_team/agents/planner.py
code_team/agents/prompter.py
code_team/agents/py.typed
code_team/agents/verifiers.py
code_team/models/__init__.py
code_team/models/config.py
code_team/models/plan.py
code_team/models/py.typed
code_team/orchestrator/__init__.py
code_team/orchestrator/orchestrator.py
code_team/orchestrator/py.typed
code_team/orchestrator/state.py
code_team/templates/AGENT_OBJECTIVITY.md
code_team/templates/ARCHITECTURE_GUIDELINES.md
code_team/templates/CODER_INSTRUCTIONS.md
code_team/templates/CODING_GUIDELINES.md
code_team/templates/COMMIT_INSTRUCTIONS.md
code_team/templates/PLANNER_INSTRUCTIONS.md
code_team/templates/PLAN_VERIFIER_INSTRUCTIONS.md
code_team/templates/PROMPTER_INSTRUCTIONS.md
code_team/templates/VERIFIER_ARCH_INSTRUCTIONS.md
code_team/templates/VERIFIER_PERF_INSTRUCTIONS.md
code_team/templates/VERIFIER_SEC_INSTRUCTIONS.md
code_team/templates/VERIFIER_TASK_INSTRUCTIONS.md
code_team/templates/claude_commands/codeteam-arch-verifier.md
code_team/templates/claude_commands/codeteam-coder.md
code_team/templates/claude_commands/codeteam-commit.md
code_team/templates/claude_commands/codeteam-perf-verifier.md
code_team/templates/claude_commands/codeteam-plan-verifier.md
code_team/templates/claude_commands/codeteam-planner.md
code_team/templates/claude_commands/codeteam-prompter.md
code_team/templates/claude_commands/codeteam-sec-verifier.md
code_team/templates/claude_commands/codeteam-task-verifier.md
code_team/utils/__init__.py
code_team/utils/exceptions.py
code_team/utils/filesystem.py
code_team/utils/git.py
code_team/utils/init.py
code_team/utils/llm.py
code_team/utils/parsing.py
code_team/utils/py.typed
code_team/utils/templates.py
code_team/utils/ui.py
code_team_framework-0.2.0.dist-info/METADATA
code_team_framework-0.2.0.dist-info/WHEEL
code_team_framework-0.2.0.dist-info/entry_points.txt
code_team_framework-0.2.0.dist-info/licenses/LICENSE
code_team_framework-0.2.0.dist-info/RECORD
